TruScanEEGpy/TruScanEEGpy.py
TruScanEEGpy/__init__.py
TruScanEEGpy/convert_channels.py
TruScanEEGpy/fix_channels.py
TruScanEEGpy/layout.py
TruScanEEGpy/montage.py
TruScanEEGpy-0.0.3.dist-info/AUTHORS.rst
TruScanEEGpy-0.0.3.dist-info/LICENSE
TruScanEEGpy-0.0.3.dist-info/METADATA
TruScanEEGpy-0.0.3.dist-info/WHEEL
TruScanEEGpy-0.0.3.dist-info/top_level.txt
TruScanEEGpy-0.0.3.dist-info/RECORD
