Metadata-Version: 2.1
Name: TruScanEEGpy
Version: 0.0.3
Summary: Utilities to work with Deymed's TruScan EEG system.
Home-page: https://github.com/neuropsychology/TruScanEEGpy
Author: Dominique Makowski
Author-email: dom.makowski@gmail.com
License: MIT license
Keywords: TruScanEEGpy
Platform: UNKNOWN
Classifier: Development Status :: 2 - Pre-Alpha
Classifier: Intended Audience :: Developers
Classifier: License :: OSI Approved :: MIT License
Classifier: Natural Language :: English
Classifier: Programming Language :: Python :: 3
Classifier: Programming Language :: Python :: 3.5
Classifier: Programming Language :: Python :: 3.6
Classifier: Programming Language :: Python :: 3.7
Requires-Dist: pandas
Requires-Dist: numpy
Requires-Dist: mne
